gdrive/__init__.py
gdrive/_version.py
gdrive/auth.py
gdrive/client.py
gdrive/exception.py
gdrive/utils.py
gdrive-0.1.5.dist-info/LICENSE
gdrive-0.1.5.dist-info/METADATA
gdrive-0.1.5.dist-info/WHEEL
gdrive-0.1.5.dist-info/top_level.txt
gdrive-0.1.5.dist-info/RECORD
