Metadata-Version: 2.1
Name: gdrive
Version: 0.1.5
Summary: Google Drive simple client
Home-page: https://github.com/kiemlicz/gdrive
Author: kiemlicz
Author-email: stanislaw.dev@gmail.com
License: UNKNOWN
Platform: UNKNOWN
Classifier: Programming Language :: Python :: 3
Classifier: License :: OSI Approved :: MIT License
Classifier: Operating System :: OS Independent
Requires-Python: >=3.6
License-File: LICENSE
